settotop/__init__.py
settotop/__main__.py
settotop/settotop.py
pysettotop-0.1.dist-info/LICENSE
pysettotop-0.1.dist-info/METADATA
pysettotop-0.1.dist-info/WHEEL
pysettotop-0.1.dist-info/entry_points.txt
pysettotop-0.1.dist-info/top_level.txt
pysettotop-0.1.dist-info/RECORD
