Metadata-Version: 2.1
Name: pysettotop
Version: 0.1
Summary: used for selecting a window and bringing it to the top of other applications.
Home-page: https://github.com/swordysrepo/settotop
Author: Swordysrepo
Author-email: swordysrepo@gmail.com
License: MIT
Download-URL: https://github.com/swordysrepo/settotop.git
Keywords: python windows top win32 settotop
Platform: UNKNOWN
Classifier: Development Status :: 3 - Alpha
Classifier: Topic :: Utilities
Classifier: Operating System :: Microsoft
Classifier: Environment :: Win32 (MS Windows)
Requires-Dist: pywin32
